{
  "type": "FeatureCollection",
  "features": [
    {
      "type": "Feature",
      "properties": {
        "stroke": "#555555",
        "stroke-width": 2,
        "stroke-opacity": 1,
        "fill": "#555555",
        "fill-opacity": 0.5,
        "name": "卧龙",
        "adcode": 411303,
        "telecode": "0377",
        "level": "district",
        "parent": "{\"name\":\"南阳\",\"level\":\"city\",\"adcode\":\"411300\",\"center\":{\"crs\":{\"type\":\"name\",\"properties\":{\"name\":\"urn:ogc:def:crs:EPSG:6.3:4326\"}},\"type\":\"Point\",\"coordinates\":[112.540918,32.999082]}}",
        "center": "{\"lng\":112.528789,\"lat\":32.989877}",
        "parentName": "南阳",
        "regionId": "2",
        "areaId": "13904"
      },
      "geometry": {
        "type": "Polygon",
        "coordinates": [
          [
            [
              112.43270874023438,
              33.258785942529386
            ],
            [
              112.42481231689453,
              33.258211766248415
            ],
            [
              112.41657257080078,
              33.256202119547524
            ],
            [
              112.4066162109375,
              33.252756903371775
            ],
            [
              112.40352630615233,
              33.24988578612424
            ],
            [
              112.40009307861328,
              33.24701457454674
            ],
            [
              112.39528656005858,
              33.24069757705509
            ],
            [
              112.39288330078125,
              33.23495445593105
            ],
            [
              112.38601684570312,
              33.23179557851464
            ],
            [
              112.38086700439453,
              33.22863658699034
            ],
            [
              112.37434387207031,
              33.22519028428529
            ],
            [
              112.36747741699219,
              33.22174384579607
            ],
            [
              112.36507415771483,
              33.22030778968541
            ],
            [
              112.36061096191406,
              33.219733360640994
            ],
            [
              112.35855102539062,
              33.2228926737125
            ],
            [
              112.35889434814453,
              33.226626260247706
            ],
            [
              112.35683441162108,
              33.23007250637392
            ],
            [
              112.35511779785156,
              33.23294427441437
            ],
            [
              112.35511779785156,
              33.23495445593105
            ],
            [
              112.34996795654297,
              33.23409295522519
            ],
            [
              112.34756469726562,
              33.23007250637392
            ],
            [
              112.34619140625,
              33.22605187269161
            ],
            [
              112.3458480834961,
              33.22231826164008
            ],
            [
              112.34447479248047,
              33.2191589278251
            ],
            [
              112.3413848876953,
              33.216861158847486
            ],
            [
              112.33726501464844,
              33.2139888627714
            ],
            [
              112.3300552368164,
              33.213414392242655
            ],
            [
              112.3238754272461,
              33.2131271555641
            ],
            [
              112.3190689086914,
              33.21283991794276
            ],
            [
              112.3187255859375,
              33.20996748987798
            ],
            [
              112.3183822631836,
              33.20537140888879
            ],
            [
              112.32009887695312,
              33.20134964006387
            ],
            [
              112.32147216796875,
              33.19847683493303
            ],
            [
              112.3238754272461,
              33.195603935546
            ],
            [
              112.32593536376952,
              33.192443637359304
            ],
            [
              112.3293685913086,
              33.190145167049636
            ],
            [
              112.33314514160155,
              33.1869846718891
            ],
            [
              112.33829498291016,
              33.185548045483564
            ],
            [
              112.34378814697266,
              33.18468605833171
            ],
            [
              112.34928131103514,
              33.18353672893615
            ],
            [
              112.3520278930664,
              33.18066333948355
            ],
            [
              112.35065460205078,
              33.17577836115719
            ],
            [
              112.34962463378906,
              33.17089311052488
            ],
            [
              112.34790802001953,
              33.16715714690634
            ],
            [
              112.34687805175781,
              33.16313362341225
            ],
            [
              112.34550476074219,
              33.159684742028034
            ],
            [
              112.34413146972656,
              33.1556608756357
            ],
            [
              112.34344482421875,
              33.15163682462206
            ],
            [
              112.34241485595703,
              33.147900040522245
            ],
            [
              112.3413848876953,
              33.14301323653333
            ],
            [
              112.34069824218749,
              33.13841364297685
            ],
            [
              112.34069824218749,
              33.13410130507293
            ],
            [
              112.34035491943358,
              33.13065128220441
            ],
            [
              112.33932495117188,
              33.12633856294882
            ],
            [
              112.33863830566406,
              33.12260070156983
            ],
            [
              112.33657836914062,
              33.11742493853135
            ],
            [
              112.33795166015625,
              33.115412059420954
            ],
            [
              112.34241485595703,
              33.115124501496844
            ],
            [
              112.3458480834961,
              33.114549382824535
            ],
            [
              112.34790802001953,
              33.111961302202765
            ],
            [
              112.35065460205078,
              33.11023587276226
            ],
            [
              112.35099792480469,
              33.105922150909976
            ],
            [
              112.3513412475586,
              33.10103301013125
            ],
            [
              112.3520278930664,
              33.09786930351166
            ],
            [
              112.35065460205078,
              33.09528073157731
            ],
            [
              112.34996795654297,
              33.09211681791773
            ],
            [
              112.35305786132812,
              33.089815718283326
            ],
            [
              112.35546112060547,
              33.08722690920878
            ],
            [
              112.35855102539062,
              33.08550099414926
            ],
            [
              112.3626708984375,
              33.08319972137792
            ],
            [
              112.36576080322266,
              33.081761395316555
            ],
            [
              112.37022399902344,
              33.08032304573328
            ],
            [
              112.3733139038086,
              33.08147372728161
            ],
            [
              112.37709045410156,
              33.08118605830584
            ],
            [
              112.38155364990234,
              33.08089838838918
            ],
            [
              112.38327026367188,
              33.077446276003094
            ],
            [
              112.3849868774414,
              33.07485710280626
            ],
            [
              112.38601684570312,
              33.07198015432512
            ],
            [
              112.38704681396484,
              33.06910311177054
            ],
            [
              112.38773345947264,
              33.067664555217014
            ],
            [
              112.39013671875,
              33.065075094158765
            ],
            [
              112.39322662353516,
              33.06191009384033
            ],
            [
              112.39494323730467,
              33.060183682059964
            ],
            [
              112.39768981933594,
              33.05816949218732
            ],
            [
              112.40180969238281,
              33.0573062538481
            ],
            [
              112.40524291992188,
              33.0535654565654
            ],
            [
              112.40867614746094,
              33.048961180184065
            ],
            [
              112.41588592529297,
              33.047234514473786
            ],
            [
              112.41966247558592,
              33.04406887274722
            ],
            [
              112.4234390258789,
              33.041190917897524
            ],
            [
              112.42378234863281,
              33.03917629355546
            ],
            [
              112.4186325073242,
              33.03485908625329
            ],
            [
              112.41279602050781,
              33.03082950191153
            ],
            [
              112.41382598876953,
              33.01989112987742
            ],
            [
              112.4062728881836,
              33.02017899916362
            ],
            [
              112.40352630615233,
              33.017588141749016
            ],
            [
              112.40764617919922,
              33.0083755876936
            ],
            [
              112.4062728881836,
              33.00117761021751
            ],
            [
              112.41279602050781,
              33.00060174664655
            ],
            [
              112.4179458618164,
              33.00204139852613
            ],
            [
              112.42172241210938,
              33.00031381345156
            ],
            [
              112.41931915283202,
              32.99369109062016
            ],
            [
              112.41451263427734,
              32.99023555965106
            ],
            [
              112.41382598876953,
              32.98764382263701
            ],
            [
              112.4172592163086,
              32.9752600288118
            ],
            [
              112.42034912109375,
              32.97324389798454
            ],
            [
              112.42069244384766,
              32.96978756663045
            ],
            [
              112.41657257080078,
              32.967483270587756
            ],
            [
              112.41451263427734,
              32.964602816005694
            ],
            [
              112.41451263427734,
              32.962010326582806
            ],
            [
              112.41828918457031,
              32.95624896663315
            ],
            [
              112.41416931152344,
              32.95250388123841
            ],
            [
              112.40867614746094,
              32.95192770016952
            ],
            [
              112.4062728881836,
              32.951639608226586
            ],
            [
              112.40352630615233,
              32.945301347928186
            ],
            [
              112.40730285644531,
              32.93435237347276
            ],
            [
              112.40283966064452,
              32.92830104287682
            ],
            [
              112.39974975585938,
              32.930318199070534
            ],
            [
              112.39597320556639,
              32.93060636048645
            ],
            [
              112.39253997802734,
              32.93204715348585
            ],
            [
              112.39151000976562,
              32.93060636048645
            ],
            [
              112.38876342773438,
              32.93060636048645
            ],
            [
              112.38807678222655,
              32.9257074887604
            ],
            [
              112.3904800415039,
              32.9257074887604
            ],
            [
              112.3897933959961,
              32.91302679651066
            ],
            [
              112.38739013671874,
              32.91302679651066
            ],
            [
              112.38704681396484,
              32.91100924613698
            ],
            [
              112.38395690917969,
              32.91158569379284
            ],
            [
              112.38224029541016,
              32.914179661793504
            ],
            [
              112.37777709960938,
              32.91446787576817
            ],
            [
              112.37606048583984,
              32.913315014239004
            ],
            [
              112.3740005493164,
              32.913891446880434
            ],
            [
              112.37262725830077,
              32.916197139908846
            ],
            [
              112.36953735351562,
              32.91533251206152
            ],
            [
              112.3681640625,
              32.913603231028915
            ],
            [
              112.37022399902344,
              32.91158569379284
            ],
            [
              112.3685073852539,
              32.90985633956465
            ],
            [
              112.36541748046875,
              32.906974007448945
            ],
            [
              112.36507415771483,
              32.89890297835098
            ],
            [
              112.3630142211914,
              32.901209061725034
            ],
            [
              112.3623275756836,
              32.90466807419695
            ],
            [
              112.35958099365234,
              32.907550481378806
            ],
            [
              112.36026763916016,
              32.9101445676153
            ],
            [
              112.35374450683594,
              32.91100924613698
            ],
            [
              112.35271453857422,
              32.92052015245145
            ],
            [
              112.35065460205078,
              32.92102449015983
            ],
            [
              112.34996795654297,
              32.919223270860584
            ],
            [
              112.34842300415039,
              32.92224929834244
            ],
            [
              112.3432731628418,
              32.92138472962035
            ],
            [
              112.34301567077635,
              32.92030400683943
            ],
            [
              112.33254432678223,
              32.919943762979564
            ],
            [
              112.33245849609375,
              32.923618181543894
            ],
            [
              112.33082771301268,
              32.92354613558754
            ],
            [
              112.32885360717772,
              32.9108651336365
            ],
            [
              112.32121467590332,
              32.91136952636176
            ],
            [
              112.31426239013672,
              32.90877547601749
            ],
            [
              112.31546401977539,
              32.90466807419695
            ],
            [
              112.31683731079102,
              32.904091581501
            ],
            [
              112.31700897216795,
              32.89890297835098
            ],
            [
              112.3157215118408,
              32.89839851460878
            ],
            [
              112.31589317321777,
              32.89681303842811
            ],
            [
              112.31374740600585,
              32.89594822127689
            ],
            [
              112.3157215118408,
              32.88946182351606
            ],
            [
              112.3135757446289,
              32.88895730600726
            ],
            [
              112.31700897216795,
              32.879226763552644
            ],
            [
              112.31237411499023,
              32.87389253140979
            ],
            [
              112.30567932128906,
              32.87324375155333
            ],
            [
              112.30224609374999,
              32.871297383497726
            ],
            [
              112.3011302947998,
              32.86264634186382
            ],
            [
              112.30224609374999,
              32.860339254897674
            ],
            [
              112.30610847473145,
              32.85781580981742
            ],
            [
              112.32181549072266,
              32.85868099907473
            ],
            [
              112.3238754272461,
              32.85255239336701
            ],
            [
              112.33074188232422,
              32.849451878635314
            ],
            [
              112.33057022094727,
              32.84613492898435
            ],
            [
              112.32464790344238,
              32.84447640766803
            ],
            [
              112.32464790344238,
              32.83863528148434
            ],
            [
              112.32670783996582,
              32.832144690492136
            ],
            [
              112.33460426330566,
              32.8235619584312
            ],
            [
              112.34241485595703,
              32.818873561262066
            ],
            [
              112.34258651733398,
              32.81173229631215
            ],
            [
              112.35795021057129,
              32.81339142924961
            ],
            [
              112.37820625305174,
              32.81202084339605
            ],
            [
              112.38241195678711,
              32.80985671742974
            ],
            [
              112.3843002319336,
              32.80466260009821
            ],
            [
              112.38447189331053,
              32.787418840308746
            ],
            [
              112.3890209197998,
              32.77645035820575
            ],
            [
              112.39314079284668,
              32.77370802639723
            ],
            [
              112.40438461303711,
              32.77168730677959
            ],
            [
              112.4106502532959,
              32.76843962556114
            ],
            [
              112.41846084594727,
              32.77168730677959
            ],
            [
              112.42661476135254,
              32.770532589256035
            ],
            [
              112.43082046508788,
              32.76966654128219
            ],
            [
              112.43425369262695,
              32.76692400043983
            ],
            [
              112.43528366088867,
              32.761871730333105
            ],
            [
              112.43433952331543,
              32.75732444210461
            ],
            [
              112.43133544921875,
              32.75631390207365
            ],
            [
              112.41914749145508,
              32.75732444210461
            ],
            [
              112.40301132202148,
              32.73826661386022
            ],
            [
              112.40060806274414,
              32.73321271803826
            ],
            [
              112.40103721618652,
              32.724837059758464
            ],
            [
              112.40429878234863,
              32.718193736786795
            ],
            [
              112.41202354431152,
              32.715160750891556
            ],
            [
              112.42472648620605,
              32.717688246300064
            ],
            [
              112.4315071105957,
              32.717616033139514
            ],
            [
              112.43708610534667,
              32.715305181130056
            ],
            [
              112.44438171386719,
              32.70931112969933
            ],
            [
              112.45081901550293,
              32.70613339692083
            ],
            [
              112.45665550231934,
              32.70483338270915
            ],
            [
              112.4636936187744,
              32.70620561937723
            ],
            [
              112.4703025817871,
              32.70389447177697
            ],
            [
              112.47193336486815,
              32.707216727628634
            ],
            [
              112.47665405273438,
              32.71032220275718
            ],
            [
              112.48197555541992,
              32.71812152403552
            ],
            [
              112.49270439147949,
              32.7224541856167
            ],
            [
              112.49914169311523,
              32.726931048100624
            ],
            [
              112.50566482543945,
              32.73566750323132
            ],
            [
              112.50575065612793,
              32.739638336131826
            ],
            [
              112.50377655029297,
              32.74469186756323
            ],
            [
              112.50077247619629,
              32.747074147255745
            ],
            [
              112.48686790466309,
              32.75082791324899
            ],
            [
              112.48180389404295,
              32.754725887428194
            ],
            [
              112.48146057128905,
              32.760428171927416
            ],
            [
              112.48403549194336,
              32.76230479329097
            ],
            [
              112.49854087829588,
              32.75782970781984
            ],
            [
              112.50369071960449,
              32.759056769764186
            ],
            [
              112.50738143920898,
              32.76208826207532
            ],
            [
              112.50360488891602,
              32.77038824851226
            ],
            [
              112.4948501586914,
              32.77305851438083
            ],
            [
              112.48995780944824,
              32.77305851438083
            ],
            [
              112.48712539672852,
              32.77558436781692
            ],
            [
              112.48661041259766,
              32.7787596247077
            ],
            [
              112.49665260314941,
              32.7887176499516
            ],
            [
              112.49691009521483,
              32.794201303793194
            ],
            [
              112.49939918518066,
              32.799179591404
            ],
            [
              112.49888420104979,
              32.80365259759099
            ],
            [
              112.49519348144531,
              32.80805323886752
            ],
            [
              112.49691009521483,
              32.82074894982263
            ],
            [
              112.5058364868164,
              32.82630275292864
            ],
            [
              112.50944137573242,
              32.82536512222339
            ],
            [
              112.52197265625,
              32.82781736623501
            ],
            [
              112.52326011657715,
              32.8296925659695
            ],
            [
              112.52377510070801,
              32.838274705544165
            ],
            [
              112.52094268798827,
              32.84108715903729
            ],
            [
              112.50454902648926,
              32.84858659937456
            ],
            [
              112.5,
              32.85305711806933
            ],
            [
              112.49845504760742,
              32.85752741152312
            ],
            [
              112.50369071960449,
              32.86336729423395
            ],
            [
              112.50300407409668,
              32.871802001540985
            ],
            [
              112.50935554504395,
              32.877280526855394
            ],
            [
              112.51175880432129,
              32.88621844654692
            ],
            [
              112.50592231750488,
              32.89083121370136
            ],
            [
              112.49819755554199,
              32.89205643961052
            ],
            [
              112.49279022216797,
              32.897245443837384
            ],
            [
              112.48867034912108,
              32.90265033334125
            ],
            [
              112.48858451843262,
              32.90481219678451
            ],
            [
              112.4849796295166,
              32.905172502227174
            ],
            [
              112.47751235961913,
              32.90978428240537
            ],
            [
              112.47528076171875,
              32.92801287395169
            ],
            [
              112.49768257141113,
              32.94213204736845
            ],
            [
              112.50171661376953,
              32.949983061332844
            ],
            [
              112.51321792602539,
              32.961578237616614
            ],
            [
              112.5190544128418,
              32.97223581531129
            ],
            [
              112.53227233886719,
              32.9846200332723
            ],
            [
              112.53450393676758,
              32.988651729407614
            ],
            [
              112.53647804260254,
              33.02111456785202
            ],
            [
              112.55484580993652,
              33.02665580958794
            ],
            [
              112.59321212768555,
              33.02924640050473
            ],
            [
              112.61303901672363,
              33.03313214409938
            ],
            [
              112.61664390563965,
              33.03507495164269
            ],
            [
              112.61621475219727,
              33.04795396263391
            ],
            [
              112.6234245300293,
              33.06054335397321
            ],
            [
              112.62883186340332,
              33.07442556653144
            ],
            [
              112.6424789428711,
              33.08852132327342
            ],
            [
              112.64453887939452,
              33.092476359295354
            ],
            [
              112.62608528137207,
              33.11548394875491
            ],
            [
              112.62445449829102,
              33.11807192559198
            ],
            [
              112.62428283691406,
              33.12482906116088
            ],
            [
              112.62986183166504,
              33.13575439297845
            ],
            [
              112.64513969421387,
              33.1435881687765
            ],
            [
              112.64668464660645,
              33.14624718139916
            ],
            [
              112.64685630798338,
              33.15372073123021
            ],
            [
              112.64410972595215,
              33.15443930823625
            ],
            [
              112.63544082641602,
              33.16686975849462
            ],
            [
              112.63269424438477,
              33.17606572036152
            ],
            [
              112.64265060424805,
              33.19093527302195
            ],
            [
              112.64076232910156,
              33.19531664042336
            ],
            [
              112.6409339904785,
              33.205084145814155
            ],
            [
              112.64350891113281,
              33.20939299295216
            ],
            [
              112.64900207519531,
              33.21283991794276
            ],
            [
              112.6439380645752,
              33.21556863728049
            ],
            [
              112.64144897460938,
              33.21506598484842
            ],
            [
              112.6399040222168,
              33.21176276846633
            ],
            [
              112.63758659362793,
              33.212480869590344
            ],
            [
              112.63801574707031,
              33.216430320446506
            ],
            [
              112.63200759887695,
              33.21872810073817
            ],
            [
              112.62771606445312,
              33.21599947992415
            ],
            [
              112.61793136596678,
              33.21793824556901
            ],
            [
              112.61827468872069,
              33.22260546814777
            ],
            [
              112.61286735534668,
              33.22310807726727
            ],
            [
              112.61183738708496,
              33.21765102373968
            ],
            [
              112.60926246643066,
              33.21765102373968
            ],
            [
              112.6095199584961,
              33.21844088150166
            ],
            [
              112.60042190551758,
              33.22181564798285
            ],
            [
              112.59964942932129,
              33.220882214958316
            ],
            [
              112.59990692138672,
              33.21671754628288
            ],
            [
              112.60119438171387,
              33.21657393348255
            ],
            [
              112.59947776794434,
              33.21556863728049
            ],
            [
              112.60025024414062,
              33.213414392242655
            ],
            [
              112.59879112243652,
              33.21169095802982
            ],
            [
              112.59243965148926,
              33.21269629877858
            ],
            [
              112.58909225463867,
              33.196968574507146
            ],
            [
              112.57364273071289,
              33.198117727664204
            ],
            [
              112.57381439208984,
              33.199266865740334
            ],
            [
              112.57132530212402,
              33.19905140349983
            ],
            [
              112.57132530212402,
              33.20134964006387
            ],
            [
              112.5636863708496,
              33.200775086578396
            ],
            [
              112.54918098449706,
              33.20558685557613
            ],
            [
              112.54231452941893,
              33.210470171594736
            ],
            [
              112.53029823303223,
              33.22727244173973
            ],
            [
              112.52961158752441,
              33.2325135152202
            ],
            [
              112.53115653991699,
              33.237610696341946
            ],
            [
              112.52720832824707,
              33.24486110396206
            ],
            [
              112.51287460327148,
              33.257350494751336
            ],
            [
              112.50755310058594,
              33.26431219626866
            ],
            [
              112.49948501586914,
              33.279310265352414
            ],
            [
              112.49493598937987,
              33.281104120242404
            ],
            [
              112.48549461364746,
              33.280099566045735
            ],
            [
              112.48008728027344,
              33.27522013836268
            ],
            [
              112.47759819030762,
              33.26811577816315
            ],
            [
              112.46875762939453,
              33.2559867975164
            ],
            [
              112.46171951293944,
              33.252182687468874
            ],
            [
              112.45511054992676,
              33.25232624179834
            ],
            [
              112.44970321655273,
              33.254048875356936
            ],
            [
              112.44309425354004,
              33.25799644917015
            ],
            [
              112.43682861328125,
              33.25892948601001
            ],
            [
              112.43270874023438,
              33.258785942529386
            ]
          ]
        ]
      }
    },
    {
      "type": "Feature",
      "properties": {
        "marker-color": "#7e7e7e",
        "marker-size": "medium",
        "marker-symbol": "",
        "name": "卧龙9厂2区",
        "parentName": "卧龙",
        "regionId": "2",
        "areaId": "13904",
        "fieldId": "15426030"
      },
      "geometry": {
        "type": "Point",
        "coordinates": [
          112.42103576660156,
          33.2139888627714
        ]
      }
    },
    {
      "type": "Feature",
      "properties": {
        "marker-color": "#7e7e7e",
        "marker-size": "medium",
        "marker-symbol": "",
        "name": "卧龙9场3区",
        "parentName": "卧龙",
        "regionId": "2",
        "areaId": "13904",
        "fieldId": "15426032"
      },
      "geometry": {
        "type": "Point",
        "coordinates": [
          112.43717193603516,
          33.19589122972613
        ]
      }
    },
    {
      "type": "Feature",
      "properties": {
        "marker-color": "#7e7e7e",
        "marker-size": "medium",
        "marker-symbol": "",
        "name": "卧龙9厂4区",
        "parentName": "卧龙",
        "regionId": "2",
        "areaId": "13904",
        "fieldId": "15426034"
      },
      "geometry": {
        "type": "Point",
        "coordinates": [
          112.43133544921875,
          33.22317987833434
        ]
      }
    },
    {
      "type": "Feature",
      "properties": {
        "marker-color": "#7e7e7e",
        "marker-size": "medium",
        "marker-symbol": "",
        "name": "卧龙21厂生长场1区",
        "parentName": "卧龙",
        "regionId": "2",
        "areaId": "13904",
        "fieldId": "15439789"
      },
      "geometry": {
        "type": "Point",
        "coordinates": [
          112.42481231689453,
          33.19273094190692
        ]
      }
    },
    {
      "type": "Feature",
      "properties": {
        "marker-color": "#7e7e7e",
        "marker-size": "medium",
        "marker-symbol": "",
        "name": "卧龙21厂生长场2区",
        "parentName": "卧龙",
        "regionId": "2",
        "areaId": "13904",
        "fieldId": "15453934"
      },
      "geometry": {
        "type": "Point",
        "coordinates": [
          112.43579864501953,
          33.212552679378675
        ]
      }
    },
    {
      "type": "Feature",
      "properties": {
        "marker-color": "#7e7e7e",
        "marker-size": "medium",
        "marker-symbol": "",
        "name": "卧龙6厂",
        "parentName": "卧龙",
        "regionId": "2",
        "areaId": "13904",
        "fieldId": "5115050"
      },
      "geometry": {
        "type": "Point",
        "coordinates": [
          112.44060516357422,
          33.17491627789081
        ]
      }
    },
    {
      "type": "Feature",
      "properties": {
        "marker-color": "#7e7e7e",
        "marker-size": "medium",
        "marker-symbol": "",
        "name": "卧龙1厂繁殖厂",
        "parentName": "卧龙",
        "regionId": "2",
        "areaId": "13904",
        "fieldId": "33583"
      },
      "geometry": {
        "type": "Point",
        "coordinates": [
          112.37503051757812,
          33.12145055836598
        ]
      }
    },
    {
      "type": "Feature",
      "properties": {
        "marker-color": "#7e7e7e",
        "marker-size": "medium",
        "marker-symbol": "",
        "name": "卧龙8厂2区",
        "parentName": "卧龙",
        "regionId": "2",
        "areaId": "13904",
        "fieldId": "15168507"
      },
      "geometry": {
        "type": "Point",
        "coordinates": [
          112.464441,
          32.755021
        ]
      }
    },
    {
      "type": "Feature",
      "properties": {
        "marker-color": "#7e7e7e",
        "marker-size": "medium",
        "marker-symbol": "",
        "name": "卧龙3厂1区",
        "parentName": "卧龙",
        "regionId": "2",
        "areaId": "13904",
        "fieldId": "37104"
      },
      "geometry": {
        "type": "Point",
        "coordinates": [
          112.460904,
          32.886092
        ]
      }
    },
    {
      "type": "Feature",
      "properties": {
        "marker-color": "#7e7e7e",
        "marker-size": "medium",
        "marker-symbol": "",
        "name": "卧龙1厂生长厂",
        "parentName": "卧龙",
        "regionId": "2",
        "areaId": "13904",
        "fieldId": "15375721"
      },
      "geometry": {
        "type": "Point",
        "coordinates": [
          112.50411987304686,
          33.16629497884489
        ]
      }
    },
    {
      "type": "Feature",
      "properties": {
        "marker-color": "#7e7e7e",
        "marker-size": "medium",
        "marker-symbol": "",
        "name": "卧龙2厂生长厂",
        "parentName": "卧龙",
        "regionId": "2",
        "areaId": "13904",
        "fieldId": "2512"
      },
      "geometry": {
        "type": "Point",
        "coordinates": [
          112.467055,
          32.855676
        ]
      }
    },
    {
      "type": "Feature",
      "properties": {
        "marker-color": "#7e7e7e",
        "marker-size": "medium",
        "marker-symbol": "",
        "name": "卧龙5厂",
        "parentName": "卧龙",
        "regionId": "2",
        "areaId": "13904",
        "fieldId": "15115183"
      },
      "geometry": {
        "type": "Point",
        "coordinates": [
          112.417253,
          32.863205
        ]
      }
    },
    {
      "type": "Feature",
      "properties": {
        "marker-color": "#7e7e7e",
        "marker-size": "medium",
        "marker-symbol": "",
        "name": "卧龙9厂1区",
        "parentName": "卧龙",
        "regionId": "2",
        "areaId": "13904",
        "fieldId": "15167073"
      },
      "geometry": {
        "type": "Point",
        "coordinates": [
          112.407995,
          32.799777
        ]
      }
    },
    {
      "type": "Feature",
      "properties": {
        "marker-color": "#7e7e7e",
        "marker-size": "medium",
        "marker-symbol": "",
        "name": "卧龙7厂",
        "parentName": "卧龙",
        "regionId": "2",
        "areaId": "13904",
        "fieldId": "15116273"
      },
      "geometry": {
        "type": "Point",
        "coordinates": [
          112.367284,
          32.8123
        ]
      }
    },
    {
      "type": "Feature",
      "properties": {
        "marker-color": "#7e7e7e",
        "marker-size": "medium",
        "marker-symbol": "",
        "name": "卧龙1厂生长厂4区",
        "parentName": "卧龙",
        "regionId": "2",
        "areaId": "13904",
        "fieldId": "33586"
      },
      "geometry": {
        "type": "Point",
        "coordinates": [
          112.37228393554686,
          33.08118605830584
        ]
      }
    },
    {
      "type": "Feature",
      "properties": {
        "marker-color": "#7e7e7e",
        "marker-size": "medium",
        "marker-symbol": "",
        "name": "卧龙一厂生长厂3区",
        "parentName": "卧龙",
        "regionId": "2",
        "areaId": "13904",
        "fieldId": "33585"
      },
      "geometry": {
        "type": "Point",
        "coordinates": [
          112.37228393554686,
          33.100745405144245
        ]
      }
    },
    {
      "type": "Feature",
      "properties": {
        "marker-color": "#7e7e7e",
        "marker-size": "medium",
        "marker-symbol": "",
        "name": "卧龙10厂",
        "parentName": "卧龙",
        "regionId": "2",
        "areaId": "13904",
        "fieldId": "15166432"
      },
      "geometry": {
        "type": "Point",
        "coordinates": [
          112.451472,
          32.903992
        ]
      }
    },
    {
      "type": "Feature",
      "properties": {
        "marker-color": "#7e7e7e",
        "marker-size": "medium",
        "marker-symbol": "",
        "name": "卧龙3厂2区",
        "parentName": "卧龙",
        "regionId": "2",
        "areaId": "13904",
        "fieldId": "25209"
      },
      "geometry": {
        "type": "Point",
        "coordinates": [
          112.460904,
          32.875097
        ]
      }
    },
    {
      "type": "Feature",
      "properties": {
        "marker-color": "#7e7e7e",
        "marker-size": "medium",
        "marker-symbol": "",
        "name": "卧龙2厂繁殖厂",
        "parentName": "卧龙",
        "regionId": "2",
        "areaId": "13904",
        "fieldId": "32865"
      },
      "geometry": {
        "type": "Point",
        "coordinates": [
          112.46,
          32.84
        ]
      }
    },
    {
      "type": "Feature",
      "properties": {
        "marker-color": "#7e7e7e",
        "marker-size": "medium",
        "marker-symbol": "",
        "name": "卧龙8厂1区",
        "parentName": "卧龙",
        "regionId": "2",
        "areaId": "13904",
        "fieldId": "15168506"
      },
      "geometry": {
        "type": "Point",
        "coordinates": [
          112.443441,
          32.755021
        ]
      }
    },
    {
      "type": "Feature",
      "properties": {
        "marker-color": "#7e7e7e",
        "marker-size": "medium",
        "marker-symbol": "",
        "name": "卧龙12厂",
        "parentName": "卧龙",
        "regionId": "2",
        "areaId": "13904",
        "fieldId": "15389773"
      },
      "geometry": {
        "type": "Point",
        "coordinates": [
          112.448888,
          32.924222
        ]
      }
    },
    {
      "type": "Feature",
      "properties": {
        "marker-color": "#7e7e7e",
        "marker-size": "medium",
        "marker-symbol": "",
        "name": "卧龙13厂",
        "parentName": "卧龙",
        "regionId": "2",
        "areaId": "13904",
        "fieldId": "15405997"
      },
      "geometry": {
        "type": "Point",
        "coordinates": [
          112.44918823242188,
          32.95797741405952
        ]
      }
    }
  ]
}